saifApi/__init__.py
saifApi/main.py
saifApi-0.1.3.dist-info/METADATA
saifApi-0.1.3.dist-info/WHEEL
saifApi-0.1.3.dist-info/top_level.txt
saifApi-0.1.3.dist-info/RECORD
