Metadata-Version: 2.1
Name: saifApi
Version: 0.1.3
Summary: A client for financial database
Home-page: UNKNOWN
Author: zzw
License: MIT
Keywords: client
Platform: UNKNOWN
Requires-Python: >=3.4
Requires-Dist: pandas (>=1.1.0)
Requires-Dist: requests
